{
  "id": "81e5734727194f54801a158248279a02",
  "name": "清仿赵执信墨迹册页",
  "era": "清",
  "category": "书法、绘画",
  "level": "二级",
  "material": "纸",
  "size": "厚2.5",
  "institution": "安丘市博物馆",
  "description": "纸本\r\n册页封面题“摹赵饴山书、杂画、书种堂墨拓”。为清人摹赵执信书法。内附李颢年画石、马炅山水等。后半部缺，附部分杂画及拓片。赵执信（1662～1744）字伸符，号秋谷、晚号饴山老人、知如老人，淄博博山人。清康熙年间进士，后任右春坊右赞善兼翰林院检讨。因佟皇后丧葬期间观看洪升《长生殿》戏剧，被劾革职。赵执信为王士祯甥婿，然论诗与其异趣，强调“文意为主，言语为役”。所作诗文深沉峭拔，亦不乏反映民生疾苦的篇目。",
  "source_url": "http://www.wwsdw.net/#/collect/detail?id=81e5734727194f54801a158248279a02",
  "crawl_time": "2026-01-18T02:07:48.955274"
}