{
  "id": "31B601126A974B3AA1DD36AC6AE9CCAF",
  "name": "北魏石佛造像",
  "era": "北魏",
  "category": "雕塑、造像",
  "level": "一级",
  "material": "石",
  "size": "",
  "institution": "青岛市博物馆",
  "description": "  头作高肉髻，是修行道行高深的象征。佛像面型削瘦适中，深目高鼻，面带微笑，内着僧袛支，束带结于胸前下垂，外着褒衣博带式正披，衣纹断面呈“V”字形，赤足立于莲花座上，莲花瓣呈尖头状，下面还有方形须弥座。佛像的手势，都是右手上扬，施无畏印，表示佛无所畏惧、庇护众生；左手下垂，掌心向外，施与愿印，表示佛满足众生的愿望，普度众生。作为我国博物馆室内陈列古代石造像，“双丈八佛”可谓体量最大，且两佛同殿并立，皆为北魏圆雕，为历史所仅存。\r\n该佛像是魏晋南北朝时期佛教造像艺术的杰出之作，为青岛市博物馆镇馆之宝之一，对研究北魏时期国家的社会政治、宗教和石雕艺术史以及山东历史文化发展等，都具有重要的价值。\r\n",
  "source_url": "http://www.wwsdw.net/#/collect/detail?id=31B601126A974B3AA1DD36AC6AE9CCAF",
  "crawl_time": "2026-01-18T03:04:40.841274"
}